{
  "doc": "http://sal.lsst.org",
  "fields": [
    {
      "name": "timestamp",
      "type": "double"
    },
    {
      "name": "timestep",
      "type": {
        "items": "double",
        "type": "array"
      }
    },
    {
      "name": "p",
      "type": {
        "items": "double",
        "type": "array"
      }
    },
    {
      "name": "i",
      "type": {
        "items": "double",
        "type": "array"
      }
    },
    {
      "name": "d",
      "type": {
        "items": "double",
        "type": "array"
      }
    },
    {
      "name": "n",
      "type": {
        "items": "double",
        "type": "array"
      }
    },
    {
      "name": "calculatedA",
      "type": {
        "items": "double",
        "type": "array"
      }
    },
    {
      "name": "calculatedB",
      "type": {
        "items": "double",
        "type": "array"
      }
    },
    {
      "name": "calculatedC",
      "type": {
        "items": "double",
        "type": "array"
      }
    },
    {
      "name": "calculatedD",
      "type": {
        "items": "double",
        "type": "array"
      }
    },
    {
      "name": "calculatedE",
      "type": {
        "items": "double",
        "type": "array"
      }
    }
  ],
  "name": "MTM1M3_logevent_pidInfo",
  "namespace": "lsst.sal",
  "sal_alias": "pidInfo",
  "sal_subsystem": "MTM1M3",
  "sal_topic_type": "SALEvent",
  "sal_version": "3.7.0",
  "type": "record"
}