{
  "doc": "http://sal.lsst.org",
  "fields": [
    {
      "doc": "Timestamp when the Kafka message was created.",
      "name": "kafka_timestamp",
      "type": {
        "logicalType": "timestamp-millis",
        "type": "long"
      }
    },
    {
      "name": "imageDir",
      "type": "string"
    },
    {
      "name": "opdDir",
      "type": "string"
    },
    {
      "name": "intraFocalVisitId",
      "type": "long"
    },
    {
      "name": "extraFocalVisitId",
      "type": "long"
    },
    {
      "name": "timestamp",
      "type": "double"
    }
  ],
  "name": "MTWEP_logevent_imageReady",
  "namespace": "lsst.sal",
  "sal_alias": "imageReady",
  "sal_subsystem": "MTWEP",
  "sal_topic_type": "SALEvent",
  "sal_version": "3.7.0",
  "type": "record"
}